gmgnapi/__init__.py
gmgnapi/client.py
gmgnapi/client_enhanced.py
gmgnapi/exceptions.py
gmgnapi/models.py
gmgnapi-0.1.0.dist-info/licenses/LICENSE
gmgnapi-0.1.0.dist-info/METADATA
gmgnapi-0.1.0.dist-info/WHEEL
gmgnapi-0.1.0.dist-info/top_level.txt
gmgnapi-0.1.0.dist-info/RECORD
