Metadata-Version: 2.4
Name: gmgnapi
Version: 0.1.0
Summary: Professional Python client for GMGN.ai WebSocket API - Real-time Solana blockchain data streams
Author-email: GmGnAPI Team <contact@gmgnapi.dev>
Maintainer-email: GmGnAPI Team <contact@gmgnapi.dev>
License: MIT
Project-URL: Homepage, https://github.com/theshadow76/GmGnAPI
Project-URL: Documentation, https://theshadow76.github.io/GmGnAPI/
Project-URL: Repository, https://github.com/theshadow76/GmGnAPI.git
Project-URL: Bug Tracker, https://github.com/theshadow76/GmGnAPI/issues
Project-URL: Changelog, https://github.com/theshadow76/GmGnAPI/releases
Project-URL: Discussions, https://github.com/theshadow76/GmGnAPI/discussions
Keywords: gmgn,gmgn-api,solana,blockchain,websocket,crypto,defi,trading,api,real-time,data,cryptocurrency,api-client,streaming
Classifier: Development Status :: 4 - Beta
Classifier: Intended Audience :: Developers
Classifier: Intended Audience :: Financial and Insurance Industry
Classifier: License :: OSI Approved :: MIT License
Classifier: Operating System :: OS Independent
Classifier: Programming Language :: Python :: 3
Classifier: Programming Language :: Python :: 3.8
Classifier: Programming Language :: Python :: 3.9
Classifier: Programming Language :: Python :: 3.10
Classifier: Programming Language :: Python :: 3.11
Classifier: Programming Language :: Python :: 3.12
Classifier: Programming Language :: Python :: 3.13
Classifier: Topic :: Internet :: WWW/HTTP
Classifier: Topic :: Office/Business :: Financial
Classifier: Topic :: Scientific/Engineering :: Information Analysis
Classifier: Topic :: Software Development :: Libraries :: Python Modules
Classifier: Topic :: System :: Networking
Classifier: Typing :: Typed
Requires-Python: >=3.8
License-File: LICENSE
Requires-Dist: websockets>=12.0
Requires-Dist: pydantic>=2.0.0
Requires-Dist: aiofiles>=23.0.0
Provides-Extra: all
Requires-Dist: pandas>=1.5.0; extra == "all"
Requires-Dist: numpy>=1.21.0; extra == "all"
Requires-Dist: aiohttp>=3.8.0; extra == "all"
Requires-Dist: sqlalchemy>=2.0.0; extra == "all"
Requires-Dist: aiosqlite>=0.19.0; extra == "all"
Provides-Extra: pandas
Requires-Dist: pandas>=1.5.0; extra == "pandas"
Provides-Extra: analysis
Requires-Dist: pandas>=1.5.0; extra == "analysis"
Requires-Dist: numpy>=1.21.0; extra == "analysis"
Provides-Extra: http
Requires-Dist: aiohttp>=3.8.0; extra == "http"
Provides-Extra: database
Requires-Dist: sqlalchemy>=2.0.0; extra == "database"
Requires-Dist: aiosqlite>=0.19.0; extra == "database"
Provides-Extra: dev
Requires-Dist: pytest>=7.0.0; extra == "dev"
Requires-Dist: pytest-asyncio>=0.21.0; extra == "dev"
Requires-Dist: pytest-cov>=4.0.0; extra == "dev"
Requires-Dist: black>=23.0.0; extra == "dev"
Requires-Dist: isort>=5.12.0; extra == "dev"
Requires-Dist: flake8>=6.0.0; extra == "dev"
Requires-Dist: mypy>=1.0.0; extra == "dev"
Requires-Dist: pre-commit>=3.0.0; extra == "dev"
Provides-Extra: docs
Requires-Dist: sphinx>=6.0.0; extra == "docs"
Requires-Dist: sphinx-rtd-theme>=1.2.0; extra == "docs"
Requires-Dist: sphinx-autodoc-typehints>=1.22.0; extra == "docs"
Provides-Extra: examples
Requires-Dist: asyncio-mqtt>=0.13.0; extra == "examples"
Requires-Dist: pandas>=1.5.0; extra == "examples"
Requires-Dist: numpy>=1.24.0; extra == "examples"
Dynamic: license-file
